reasoning_from_scratch/__init__.py
reasoning_from_scratch/appendix_c.py
reasoning_from_scratch/appendix_f.py
reasoning_from_scratch/ch02.py
reasoning_from_scratch/ch02_ex.py
reasoning_from_scratch/ch03.py
reasoning_from_scratch/ch04.py
reasoning_from_scratch/ch05.py
reasoning_from_scratch/ch06.py
reasoning_from_scratch/qwen3.py
reasoning_from_scratch/qwen3_batched.py
reasoning_from_scratch/qwen3_optimized.py
reasoning_from_scratch/utils.py
reasoning_from_scratch-0.1.13.dist-info/licenses/LICENSE
reasoning_from_scratch-0.1.13.dist-info/METADATA
reasoning_from_scratch-0.1.13.dist-info/WHEEL
reasoning_from_scratch-0.1.13.dist-info/top_level.txt
reasoning_from_scratch-0.1.13.dist-info/RECORD
