Metadata-Version: 2.4
Name: reasoning_from_scratch
Version: 0.1.13
Summary: Reasoning Models From Scratch
Author: Sebastian Raschka
License:                                  Apache License
Classifier: License :: OSI Approved :: Apache Software License
Classifier: Programming Language :: Python :: 3.10
Classifier: Programming Language :: Python :: 3.11
Classifier: Programming Language :: Python :: 3.12
Classifier: Programming Language :: Python :: 3.13
Classifier: Intended Audience :: Developers
Classifier: Operating System :: OS Independent
Requires-Python: >=3.10
License-File: LICENSE
Requires-Dist: jupyterlab>=4.4.7
Requires-Dist: torch>=2.7.1
Requires-Dist: tokenizers>=0.21.2
Requires-Dist: nbformat>=5.10.4
Requires-Dist: sympy>=1.14.0
Requires-Dist: matplotlib>=3.10.7
Dynamic: license-file
